{
  "event_series_photo_action::clip_card_2::goals[0]": "Replicate the composition of the first photo with a different person.", 
  "event_series_photo_action::evaluation_card_0::text": "--------", 
  "event_series_photo_action::clip_card_1::goals[0]": "Replicate the composition of the first photo with a different person.", 
  "event_series_photo_action::clip_card_4::goals[0]": "Replicate the composition of the first photo with a different person.", 
  "event_series_photo_action::clip_card_0::goals[0]": "You might photograph a person performing a common action at the event.", 
  "event_series_photo_action::clip_card_3::goals[0]": "Replicate the composition of the first photo with a different person."
}